{"T633UvZZF18PMxEWgWHG0A==":"foto%20mia-329x308.jpg","o0Qcm81v4zggSktqKt0ewg==":"foto%20mia-329x308.jpeg","THOdjmUpVMYJ7GBSKNtdIg==":"foto%20mia-329x308.jpeg","soI77HKuNpWMajyYTcqUdw==":"foto%20mia-329x308.jpeg","Yr37u899w9vR2rp6e16vew==":"background7.jpeg","nvgHAneyoLdObQ09zYxoXA==":"pacs%20code-506x176.png","eZZ2BzN8bxRJlFdSIQ4xDg==":"pacs%20code-506x176.png","D8b0MK6UF0FNgA888awhZw==":"pacs%20code-506x131.png","roxxKeHJaQu723P+tbtZ3A==":"pacs%20code-506x131.png","QJYamZ6KgE2i3VGeFb7BGg==":"pacs%20code-506x131.png","meAmeG4t7E8Bjly7d3rQhg==":"pacs%20code-506x338.png","XJ7BwtBc+fPSYp54xC/Yew==":"piiot%20architecture-506x338.png","bW2nSC9V4foIpnMALuHrcA==":"sodexo%20architecture-506x338.png","G+MOthX/guEBkrM7kAVPKw==":"piiot%20mapa-646x431.png","3dS+KRqead4voSwBufCu5g==":"macops-646x363.png","gsaaDrCfy8Cfitzfye65XA==":"macops-646x431.png","xeIl6WhnHHerltSDMpOd0w==":"background1-1600x1067.jpg","TCOWh9St8UbyC7/GPQz6kw==":"glasses-1052010-640-640x480.jpg","wlYjr5iQFeAjPjs/0hHdgw==":"background1-1600x1067.jpeg","Zr2f9+v8L/8IJdA7xD6jcQ==":"istockphoto-1091348950-612x408.jpg","43Z3cIkur8YqukiOVVXq7g==":"img-20210728-wa0037-506x270.jpg","dTvfdPnq5D62uQcCM8yBEQ==":"img-20210728-wa0036-506x243.jpg","NeU3GwjtPkSQxnPPaTdajw==":"img-20210728-wa0036-646x310.jpg","+LcSM+vQg5cgyZiRnR/2xA==":"img-20210728-wa0036(camara)-643x431.jpg","APYPkwVEK6OmZle3/A77mg==":"img-20210728-wa0039(userprofile)-641x431.jpg"}